{
  "season": "2022",
  "round": "10",
  "url": "https://en.wikipedia.org/wiki/2022_British_Grand_Prix",
  "raceName": "British Grand Prix",
  "Circuit": {
    "circuitId": "silverstone",
    "url": "https://en.wikipedia.org/wiki/Silverstone_Circuit",
    "circuitName": "Silverstone Circuit",
    "Location": {
      "lat": "52.0786",
      "long": "-1.01694",
      "locality": "Silverstone",
      "country": "UK"
    }
  },
  "date": "2022-07-03",
  "time": "14:00:00Z",
  "FirstPractice": {
    "date": "2022-07-01",
    "time": "12:00:00Z"
  },
  "SecondPractice": {
    "date": "2022-07-01",
    "time": "15:00:00Z"
  },
  "ThirdPractice": {
    "date": "2022-07-02",
    "time": "11:00:00Z"
  },
  "Qualifying": {
    "date": "2022-07-02",
    "time": "14:00:00Z"
  }
}